{"name":"build-javascript","namedChunkGroups":{"app":{"name":"app","assets":[{"name":"webpack-runtime-aa293facd1d51581e600.js","size":5251},{"name":"framework-16f1f506aec5c9baf9a9.js","size":140737},{"name":"app-97cfa327c95d62910a2f.js","size":104964}],"filteredAssets":0,"assetsSize":250952,"filteredAuxiliaryAssets":3,"auxiliaryAssetsSize":719441},"component---src-pages-404-tsx":{"name":"component---src-pages-404-tsx","assets":[{"name":"component---src-pages-404-tsx-e09f7834147111e88f94.js","size":1921}],"filteredAssets":0,"assetsSize":1921,"filteredAuxiliaryAssets":1,"auxiliaryAssetsSize":4842},"component---src-pages-about-tsx":{"name":"component---src-pages-about-tsx","assets":[{"name":"styles.19e19b4450e82a18812e.css","size":24969},{"name":"component---src-pages-about-tsx-78fb6aa72c2b96b19e18.js","size":3707}],"filteredAssets":0,"assetsSize":28676,"filteredAuxiliaryAssets":1,"auxiliaryAssetsSize":9896},"component---src-pages-contact-tsx":{"name":"component---src-pages-contact-tsx","assets":[{"name":"styles.19e19b4450e82a18812e.css","size":24969},{"name":"component---src-pages-contact-tsx-6064e113b50ea14fd53e.js","size":6541}],"filteredAssets":0,"assetsSize":31510,"filteredAuxiliaryAssets":4,"auxiliaryAssetsSize":65675},"component---src-pages-index-tsx":{"name":"component---src-pages-index-tsx","assets":[{"name":"styles.19e19b4450e82a18812e.css","size":24969},{"name":"ea88be26-8db191f999cde29af27e.js","size":296061},{"name":"component---src-pages-index-tsx-1934a34f32c159259bc8.js","size":337570}],"filteredAssets":0,"assetsSize":658600,"filteredAuxiliaryAssets":2,"auxiliaryAssetsSize":1259672},"component---src-pages-work-tsx":{"name":"component---src-pages-work-tsx","assets":[{"name":"styles.19e19b4450e82a18812e.css","size":24969},{"name":"component---src-pages-work-tsx-04c7a0382e37b186b5bd.js","size":24920}],"filteredAssets":0,"assetsSize":49889,"filteredAuxiliaryAssets":1,"auxiliaryAssetsSize":147713}},"assetsByChunkName":{"app":["webpack-runtime-aa293facd1d51581e600.js","framework-16f1f506aec5c9baf9a9.js","app-97cfa327c95d62910a2f.js"],"component---src-pages-404-tsx":["component---src-pages-404-tsx-e09f7834147111e88f94.js"],"component---src-pages-about-tsx":["styles.19e19b4450e82a18812e.css","component---src-pages-about-tsx-78fb6aa72c2b96b19e18.js"],"component---src-pages-contact-tsx":["styles.19e19b4450e82a18812e.css","component---src-pages-contact-tsx-6064e113b50ea14fd53e.js"],"component---src-pages-index-tsx":["styles.19e19b4450e82a18812e.css","ea88be26-8db191f999cde29af27e.js","component---src-pages-index-tsx-1934a34f32c159259bc8.js"],"component---src-pages-work-tsx":["styles.19e19b4450e82a18812e.css","component---src-pages-work-tsx-04c7a0382e37b186b5bd.js"]},"childAssetsByChunkName":{}}